permissify/__init__.py
permissify/admin.py
permissify/apps.py
permissify/backends.py
permissify/drf/__init__.py
permissify/drf/permissions.py
permissify/management/__init__.py
permissify/management/commands/__init__.py
permissify/management/commands/add_role.py
permissify/management/commands/remove_role.py
permissify/managers.py
permissify/migrations/0001_initial.py
permissify/migrations/__init__.py
permissify/models.py
permissify/shortcuts.py
permissify/utils.py
django_permissify-1.0.6.dist-info/METADATA
django_permissify-1.0.6.dist-info/WHEEL
django_permissify-1.0.6.dist-info/RECORD
