Metadata-Version: 2.1
Name: django-permissify
Version: 1.0.6
Summary: Django Object Permissions
Home-page: https://github.com/dmp593/django-permissify
License: MIT
Keywords: Django,Permissions,Object Permissions
Author: Daniel Pinto
Author-email: dmp593@gmail.com
Requires-Python: >=3.10,<4.0
Classifier: Environment :: Web Environment
Classifier: Framework :: Django
Classifier: Framework :: Django :: 4.0
Classifier: Framework :: Django :: 4.1
Classifier: Framework :: Django :: 4.2
Classifier: Framework :: Django :: 5.0
Classifier: Intended Audience :: Developers
Classifier: License :: OSI Approved :: MIT License
Classifier: Operating System :: OS Independent
Classifier: Programming Language :: Python
Classifier: Programming Language :: Python :: 3
Classifier: Programming Language :: Python :: 3.10
Classifier: Programming Language :: Python :: 3.11
Classifier: Programming Language :: Python :: 3.12
Classifier: Programming Language :: Python :: 3 :: Only
Classifier: Topic :: Software Development :: Libraries
Classifier: Topic :: Software Development :: Libraries :: Application Frameworks
Provides-Extra: drf
Requires-Dist: Django (>=5.0,<6.0)
Requires-Dist: djangorestframework (>=3.15,<4.0) ; extra == "drf"
Project-URL: Repository, https://github.com/dmp593/django-permissify
